vault/__init__.py
vault/__main__.py
vault/parser.py
vault/utils.py
vault/vault.py
vault_recovery-0.3.dist-info/LICENSE
vault_recovery-0.3.dist-info/METADATA
vault_recovery-0.3.dist-info/WHEEL
vault_recovery-0.3.dist-info/entry_points.txt
vault_recovery-0.3.dist-info/top_level.txt
vault_recovery-0.3.dist-info/RECORD
