Metadata-Version: 2.1
Name: vault_recovery
Version: 0.3
Summary: Tool for a disaster recovery of Odoo's vault module
Home-page: https://github.com/fkantelberg/vault-recovery
Author: Florian Kantelberg
Author-email: florian.kantelberg@mailbox.org
License: MIT
Keywords: vault disaster recovery
Classifier: License :: OSI Approved :: MIT License
Classifier: Operating System :: OS Independent
Classifier: Programming Language :: Python :: 3
Requires-Python: >=3.10
License-File: LICENSE
Requires-Dist: cryptography
Requires-Dist: psycopg2
Requires-Dist: typing-extensions
